Products.ExtendedPathIndex-5.0.0-py3.13-nspkg.pth
Products/ExtendedPathIndex/ExtendedPathIndex.py
Products/ExtendedPathIndex/__init__.py
Products/ExtendedPathIndex/dtml/addExtendedPathIndex.dtml
Products/ExtendedPathIndex/tests/__init__.py
Products/ExtendedPathIndex/tests/testExtendedPathIndex.py
Products/ExtendedPathIndex/tests/testIndexedAttrs.py
Products/ExtendedPathIndex/www/index.gif
products_extendedpathindex-5.0.0.dist-info/METADATA
products_extendedpathindex-5.0.0.dist-info/WHEEL
products_extendedpathindex-5.0.0.dist-info/namespace_packages.txt
products_extendedpathindex-5.0.0.dist-info/top_level.txt
products_extendedpathindex-5.0.0.dist-info/RECORD
